nonebot_plugin_onebot_monitor/__init__.py
nonebot_plugin_onebot_monitor/config.py
nonebot_plugin_onebot_monitor/handle_request.py
nonebot_plugin_onebot_monitor/models/__init__.py
nonebot_plugin_onebot_monitor/models/notice.py
nonebot_plugin_onebot_monitor/models/request.py
nonebot_plugin_onebot_monitor/monitor_notice.py
nonebot_plugin_onebot_monitor/monitor_request.py
nonebot_plugin_onebot_monitor/query_notice.py
nonebot_plugin_onebot_monitor/query_request.py
nonebot_plugin_onebot_monitor/utils.py
nonebot_plugin_onebot_monitor-0.1.2.dist-info/WHEEL
nonebot_plugin_onebot_monitor-0.1.2.dist-info/METADATA
nonebot_plugin_onebot_monitor-0.1.2.dist-info/RECORD
