Metadata-Version: 2.1
Name: nonebot-plugin-onebot-monitor
Version: 0.1.2
Summary: 
License: MIT
Author: ssttkkl
Author-email: huang.wen.long@hotmail.com
Requires-Python: >=3.9,<4.0
Classifier: License :: OSI Approved :: MIT License
Classifier: Programming Language :: Python :: 3
Classifier: Programming Language :: Python :: 3.9
Classifier: Programming Language :: Python :: 3.10
Classifier: Programming Language :: Python :: 3.11
Requires-Dist: aiosqlite (>=0.17.0,<0.18.0)
Requires-Dist: cachetools (>=5.2.0,<6.0.0)
Requires-Dist: nonebot-adapter-onebot (>=2.1.3,<3.0.0)
Requires-Dist: nonebot-plugin-sqlalchemy (>=0.1.0,<0.2.0)
Requires-Dist: nonebot2 (>=2.0.0-rc.1,<3.0.0)
